linpgassets/LICENSE
linpgassets/README.md
linpgassets/__init__.py
linpgassets/py.typed
linpgassets/__pyinstaller/__init__.py
linpgassets/__pyinstaller/hook-linpgassets.py
linpgassets/config/database.json
linpgassets/image/environment/decorations.png.linpg.meta
linpgassets/image/environment/decorations.png.zip
linpgassets/image/environment/tiles.png.linpg.meta
linpgassets/image/environment/tiles.png.zip
linpgassets/image/user_interface/add.png.zip
linpgassets/image/user_interface/auto.png.zip
linpgassets/image/user_interface/back.png.zip
linpgassets/image/user_interface/button.png.zip
linpgassets/image/user_interface/container.png.zip
linpgassets/image/user_interface/container_button.png.zip
linpgassets/image/user_interface/delete.png.zip
linpgassets/image/user_interface/deselect.png.zip
linpgassets/image/user_interface/hide.png.zip
linpgassets/image/user_interface/history.png.zip
linpgassets/image/user_interface/mute.png.zip
linpgassets/image/user_interface/next.png.zip
linpgassets/image/user_interface/option.png.zip
linpgassets/image/user_interface/option_selected.png.zip
linpgassets/image/user_interface/previous.png.zip
linpgassets/image/user_interface/reload.png.zip
linpgassets/image/user_interface/rescale.png.zip
linpgassets/image/user_interface/save.png.zip
linpgassets/image/user_interface/setting_bar_circle.png.zip
linpgassets/image/user_interface/setting_bar_empty.png.zip
linpgassets/image/user_interface/setting_bar_full.png.zip
linpgassets-24.12.dist-info/LICENSE
linpgassets-24.12.dist-info/METADATA
linpgassets-24.12.dist-info/WHEEL
linpgassets-24.12.dist-info/entry_points.txt
linpgassets-24.12.dist-info/top_level.txt
linpgassets-24.12.dist-info/RECORD
