Metadata-Version: 2.1
Name: linpgassets
Version: 24.12
Summary: An add-on created by Tigeia Workshop that temporarily provides assets for no-commercial educational personal usage.
Author-email: Linpg Foundation <yudong9912@gmail.com>
Project-URL: Bug Tracker, https://github.com/LinpgFoundation/linpg-assets/issues
Project-URL: Homepage, https://github.com/LinpgFoundation/linpg-assets
Classifier: Operating System :: OS Independent
Classifier: Programming Language :: Python :: 3.11
Classifier: Programming Language :: Python :: 3.12
Classifier: Programming Language :: Python :: 3.13
Classifier: Programming Language :: Python :: Implementation :: CPython
Requires-Python: >=3.11
License-File: LICENSE
